aoc/__init__.py
aoc/helpers.py
aoc/template.py
aoc/version.py
advent_of_code_helpers-0.1.1.dist-info/LICENSE
advent_of_code_helpers-0.1.1.dist-info/METADATA
advent_of_code_helpers-0.1.1.dist-info/WHEEL
advent_of_code_helpers-0.1.1.dist-info/top_level.txt
advent_of_code_helpers-0.1.1.dist-info/RECORD
