Metadata-Version: 2.1
Name: advent-of-code-helpers
Version: 0.1.1
Summary: Advent of Code helper functions
Home-page: https://github.com/mvaal/advent-of-code-helpers
Author: Marcus Vaal
Author-email: mjvaal@gmail.com
Maintainer: Marcus Vaal
Maintainer-email: mjvaal@gmail.com
License: MIT License
Keywords: python,advent of code,aoc
Platform: UNKNOWN
Classifier: Operating System :: OS Independent
Classifier: Topic :: Software Development :: Libraries
Classifier: License :: OSI Approved :: MIT License
Classifier: Programming Language :: Python :: 3.8
Classifier: Programming Language :: Python :: 3.7
Classifier: Programming Language :: Python :: 3.6
Requires-Python: >=3.5
Provides-Extra: dev
Requires-Dist: pytest ; extra == 'dev'
Provides-Extra: test
Requires-Dist: pytest ; extra == 'test'
